memcachio/__init__.py
memcachio/_version.py
memcachio/_version.pyi
memcachio/authentication.py
memcachio/client.py
memcachio/commands.py
memcachio/compat.py
memcachio/connection.py
memcachio/constants.py
memcachio/defaults.py
memcachio/errors.py
memcachio/pool.py
memcachio/py.typed
memcachio/routing.py
memcachio/types.py
memcachio/utils.py
memcachio-0.5.1.dist-info/METADATA
memcachio-0.5.1.dist-info/WHEEL
memcachio-0.5.1.dist-info/licenses/LICENSE.txt
memcachio-0.5.1.dist-info/RECORD
