Metadata-Version: 2.4
Name: memcachio
Version: 0.5.1
Summary: Python async client for Memcached
Project-URL: Homepage, https://memcachio.readthedocs.org
Project-URL: Source, https://github.com/alisaifee/memcachio
Project-URL: Documentation, https://memcachio.readthedocs.org
Author-email: Ali-Akber Saifee <ali@indydevs.org>
Maintainer-email: Ali-Akber Saifee <ali@indydevs.org>
License-Expression: MIT
License-File: LICENSE.txt
Keywords: Memcached,asyncio
Classifier: Development Status :: 4 - Beta
Classifier: Intended Audience :: Developers
Classifier: Operating System :: OS Independent
Classifier: Programming Language :: Python
Classifier: Programming Language :: Python :: 3.11
Classifier: Programming Language :: Python :: 3.12
Classifier: Programming Language :: Python :: 3.13
Classifier: Programming Language :: Python :: Implementation :: PyPy
Requires-Python: >=3.10
Requires-Dist: async-timeout<6,>5; python_version < '3.11'
Requires-Dist: typing-extensions>=4.3; python_version < '3.11'
